src/zendesk_mcp_server/__init__.py
src/zendesk_mcp_server/server.py
src/zendesk_mcp_server/zendesk_client.py
orange_zendesk_mcp_server-0.1.0.dist-info/METADATA
orange_zendesk_mcp_server-0.1.0.dist-info/WHEEL
orange_zendesk_mcp_server-0.1.0.dist-info/entry_points.txt
orange_zendesk_mcp_server-0.1.0.dist-info/licenses/LICENSE
orange_zendesk_mcp_server-0.1.0.dist-info/RECORD
