Metadata-Version: 2.4
Name: orange-zendesk-mcp-server
Version: 0.1.0
Summary: A simple Zendesk MCP server
License-File: LICENSE
Requires-Python: >=3.12
Requires-Dist: mcp>=1.1.2
Requires-Dist: python-dotenv>=1.0.1
Requires-Dist: zenpy>=2.0.56
